<?xml version="1.0" encoding="UTF-8" ?>
<class name="JigsawParameterFormattedText" inherits="JigsawParameter" xmlns:xsi="http://www.w3.org/2001/XMLSchema-instance" xsi:noNamespaceSchemaLocation="https://raw.githubusercontent.com/godotengine/godot/master/doc/class.xsd">
	<brief_description>
	</brief_description>
	<description>
	</description>
	<tutorials>
	</tutorials>
	<members>
		<member name="text" type="FormattedText[]" setter="set_text" getter="get_text" default="[]">
		</member>
		<member name="type" type="int" setter="" getter="get_type" overrides="JigsawParameter" enum="JigsawParameter.Type" default="-3" />
	</members>
</class>
